MANIFEST.in
README.rst
requirements.txt
setup.py
custom_vision_client/__init__.py
custom_vision_client/client.py
custom_vision_client/exceptions.py
custom_vision_client/models.py
custom_vision_client/prediction.py
custom_vision_client/training.py
custom_vision_client.egg-info/PKG-INFO
custom_vision_client.egg-info/SOURCES.txt
custom_vision_client.egg-info/dependency_links.txt
custom_vision_client.egg-info/requires.txt
custom_vision_client.egg-info/top_level.txt