Metadata-Version: 1.0
Name: custom-vision-client
Version: 0.0.4
Summary: A client for the Microsoft Azure Custom Vision Service
Home-page: https://github.com/CatalystCode/py_custom_vision_client
Author: Clemens Wolff
Author-email: clewolff@microsoft.com
License: License :: OSI Approved :: MIT License
Platform: UNKNOWN
